workdir/__init__.py
workdir/_version.py
workdir-0.3.5.dist-info/DESCRIPTION.rst
workdir-0.3.5.dist-info/METADATA
workdir-0.3.5.dist-info/RECORD
workdir-0.3.5.dist-info/WHEEL
workdir-0.3.5.dist-info/metadata.json
workdir-0.3.5.dist-info/top_level.txt
