Metadata-Version: 2.0
Name: workdir
Version: 0.3.5
Summary: Simple module for easily isolating temporary file I/O
Home-page: https://github.com/ajk8/workdir-python
Author: Adam Kaufman
Author-email: kaufman.blue@gmail.com
License: MIT
Download-URL: https://github.com/ajk8/workdir-python/tarball/0.3.5
Keywords: development workdir isolate temporary working directory
Platform: UNKNOWN
Classifier: Development Status :: 3 - Alpha
Classifier: Intended Audience :: Developers
Classifier: License :: OSI Approved :: MIT License
Classifier: Natural Language :: English
Classifier: Operating System :: OS Independent
Classifier: Programming Language :: Python :: 2
Classifier: Programming Language :: Python :: 2.6
Classifier: Programming Language :: Python :: 2.7
Classifier: Programming Language :: Python :: 3
Classifier: Programming Language :: Python :: 3.3
Classifier: Programming Language :: Python :: 3.4
Classifier: Programming Language :: Python :: 3.5
Classifier: Topic :: Software Development
Classifier: Topic :: Software Development :: Libraries :: Python Modules
Requires-Dist: dirsync (>=2.2.1)
Requires-Dist: funcy (>=1.4)
Requires-Dist: six
